ghcopy/__init__.py
ghcopy/__main__.py
ghcopy/config/__init__.py
ghcopy/utils/__init__.py
ghcopy-0.0.3.dist-info/LICENSE
ghcopy-0.0.3.dist-info/METADATA
ghcopy-0.0.3.dist-info/WHEEL
ghcopy-0.0.3.dist-info/entry_points.txt
ghcopy-0.0.3.dist-info/top_level.txt
ghcopy-0.0.3.dist-info/RECORD
