Metadata-Version: 2.1
Name: ghcopy
Version: 0.0.3
Summary: Clone, fetch, pull user's Github repositories
Home-page: https://github.com/oleglpts/github-copier
Author: Oleg Lupats
Author-email: oleglupats@gmail.com
License: MIT
Platform: any
Classifier: Operating System :: POSIX
Classifier: Programming Language :: Python :: 3
Classifier: Programming Language :: Python :: 3.5
Requires-Python: >=3
Requires-Dist: GitPython (>=3.0.8)
Requires-Dist: PyGithub (>=1.46)
Requires-Dist: bitbucket-python (>=0.2.2)
